gptc/__init__.py
gptc/__main__.py
gptc/classifier.py
gptc/compiler.py
gptc/exceptions.py
gptc/model.py
gptc/pack.py
gptc/tokenizer.py
gptc/weighting.py
gptc-4.0.1.dist-info/LICENSE
gptc-4.0.1.dist-info/METADATA
gptc-4.0.1.dist-info/WHEEL
gptc-4.0.1.dist-info/entry_points.txt
gptc-4.0.1.dist-info/top_level.txt
gptc-4.0.1.dist-info/RECORD
