Metadata-Version: 2.1
Name: gptc
Version: 4.0.1
Summary: General-purpose text classifier
Author-email: Samuel Sloniker <sam@kj7rrv.com>
Project-URL: Homepage, https://git.kj7rrv.com/kj7rrv/gptc
Classifier: Programming Language :: Python
Classifier: Programming Language :: Python :: 3
Classifier: Development Status :: 5 - Production/Stable
Classifier: License :: OSI Approved :: GNU General Public License v3 or later (GPLv3+)
Classifier: Operating System :: OS Independent
Requires-Python: >=3.7
License-File: LICENSE
Requires-Dist: emoji
